MANIFEST.in
README.md
setup.py
s3tup/__init__.py
s3tup/bucket.py
s3tup/cli.py
s3tup/connection.py
s3tup/constants.py
s3tup/exception.py
s3tup/key.py
s3tup/parse.py
s3tup/rsync.py
s3tup/utils.py
s3tup.egg-info/PKG-INFO
s3tup.egg-info/SOURCES.txt
s3tup.egg-info/dependency_links.txt
s3tup.egg-info/entry_points.txt
s3tup.egg-info/not-zip-safe
s3tup.egg-info/requires.txt
s3tup.egg-info/top_level.txt
tests/__init__.py
tests/test_bucket.py
tests/test_connection.py
tests/test_key.py
tests/test_parse.py
tests/test_rsync.py
tests/test_utils.py
tests/utils.py