Metadata-Version: 1.1
Name: s3tup
Version: 0.1.0
Summary: Declarative configuration management and deployment tool for amazon s3
Home-page: http://github.com/HeyImAlex/s3tup
Author: Alex Guerra
Author-email: alex@heyimalex.com
License: MIT
Keywords: s3 declarative config deploy
Platform: UNKNOWN
Classifier: Development Status :: 3 - Alpha
Classifier: License :: OSI Approved :: MIT License
Classifier: Programming Language :: Python :: 2.7
